adafruit_mpl3115a2.py
adafruit_circuitpython_mpl3115a2-3.0.10.dist-info/licenses/LICENSE
adafruit_circuitpython_mpl3115a2-3.0.10.dist-info/METADATA
adafruit_circuitpython_mpl3115a2-3.0.10.dist-info/WHEEL
adafruit_circuitpython_mpl3115a2-3.0.10.dist-info/top_level.txt
adafruit_circuitpython_mpl3115a2-3.0.10.dist-info/RECORD
