Metadata-Version: 2.4
Name: adafruit-circuitpython-mpl3115a2
Version: 3.0.10
Summary: CircuitPython library for MPL3115A2 barometric pressure and temperature sensor.
Author-email: Adafruit Industries <circuitpython@adafruit.com>
License: MIT
Project-URL: Homepage, https://github.com/adafruit/Adafruit_CircuitPython_MPL3115A2
Keywords: adafruit,mpl3115a2,barometric,pressure,temperature,sensor,breakout,hardwaremicropython,circuitpython
Classifier: Intended Audience :: Developers
Classifier: Topic :: Software Development :: Libraries
Classifier: Topic :: Software Development :: Embedded Systems
Classifier: Topic :: System :: Hardware
Classifier: License :: OSI Approved :: MIT License
Classifier: Programming Language :: Python :: 3
License-File: LICENSE
Requires-Dist: Adafruit-Blinka
Requires-Dist: adafruit-circuitpython-busdevice
Provides-Extra: optional
Dynamic: license-file
